marianodoc/__init__.py
marianodoc/previous/__init__.py
marianodoc/pytransform/__init__.py
marianodoc-1.0.13.dist-info/METADATA
marianodoc-1.0.13.dist-info/WHEEL
marianodoc-1.0.13.dist-info/top_level.txt
marianodoc-1.0.13.dist-info/RECORD
