Metadata-Version: 2.1
Name: marianodoc
Version: 1.0.13
Summary: Produce WORD and PDF files with great ease, examples provided on import 
Home-page: UNKNOWN
Author: Mariano Rico
Author-email: <marianoricoPy@gmail.com>
License: UNKNOWN
Keywords: MS WORD,PDF,Word
Platform: UNKNOWN
Classifier: Development Status :: 1 - Planning
Classifier: Intended Audience :: Developers
Classifier: Programming Language :: Python :: 3
Classifier: Operating System :: Unix
Classifier: Operating System :: MacOS :: MacOS X
Classifier: Operating System :: Microsoft :: Windows
Requires-Dist: fpdf2
Requires-Dist: python-docx
